{
  "troubleshoot_default_gateway": {
    "precision": 1.0,
    "recall": 1.0,
    "f1-score": 1.0,
    "support": 4,
    "confused_with": {}
  },
  "wireless_printer_setup": {
    "precision": 1.0,
    "recall": 1.0,
    "f1-score": 1.0,
    "support": 6,
    "confused_with": {}
  },
  "vpn_connection_setup": {
    "precision": 1.0,
    "recall": 1.0,
    "f1-score": 1.0,
    "support": 7,
    "confused_with": {}
  },
  "troubleshoot_network_path": {
    "precision": 1.0,
    "recall": 1.0,
    "f1-score": 1.0,
    "support": 4,
    "confused_with": {}
  },
  "security_incident_reporting": {
    "precision": 1.0,
    "recall": 1.0,
    "f1-score": 1.0,
    "support": 6,
    "confused_with": {}
  },
  "troubleshoot_ip_conflict": {
    "precision": 1.0,
    "recall": 1.0,
    "f1-score": 1.0,
    "support": 4,
    "confused_with": {}
  },
  "email_access_remote": {
    "precision": 1.0,
    "recall": 1.0,
    "f1-score": 1.0,
    "support": 6,
    "confused_with": {}
  },
  "query_setup_guest_network": {
    "precision": 1.0,
    "recall": 1.0,
    "f1-score": 1.0,
    "support": 3,
    "confused_with": {}
  },
  "bot_challenge": {
    "precision": 1.0,
    "recall": 0.25,
    "f1-score": 0.4,
    "support": 4,
    "confused_with": {
      "firewall_working": 2,
      "affirm": 1
    }
  },
  "query_network_security": {
    "precision": 1.0,
    "recall": 1.0,
    "f1-score": 1.0,
    "support": 5,
    "confused_with": {}
  },
  "assign_work": {
    "precision": 1.0,
    "recall": 1.0,
    "f1-score": 1.0,
    "support": 4,
    "confused_with": {}
  },
  "firewall_working": {
    "precision": 0.75,
    "recall": 1.0,
    "f1-score": 0.8571428571428571,
    "support": 6,
    "confused_with": {}
  },
  "troubleshoot_network_cable_broken": {
    "precision": 1.0,
    "recall": 1.0,
    "f1-score": 1.0,
    "support": 8,
    "confused_with": {}
  },
  "orange": {
    "precision": 1.0,
    "recall": 1.0,
    "f1-score": 1.0,
    "support": 5,
    "confused_with": {}
  },
  "computer_performance_optimization": {
    "precision": 1.0,
    "recall": 1.0,
    "f1-score": 1.0,
    "support": 6,
    "confused_with": {}
  },
  "submit_query": {
    "precision": 1.0,
    "recall": 1.0,
    "f1-score": 1.0,
    "support": 6,
    "confused_with": {}
  },
  "cancel_flight": {
    "precision": 1.0,
    "recall": 1.0,
    "f1-score": 1.0,
    "support": 8,
    "confused_with": {}
  },
  "network_drive_mapping": {
    "precision": 1.0,
    "recall": 1.0,
    "f1-score": 1.0,
    "support": 6,
    "confused_with": {}
  },
  "book_flight": {
    "precision": 1.0,
    "recall": 1.0,
    "f1-score": 1.0,
    "support": 8,
    "confused_with": {}
  },
  "network_password_reset": {
    "precision": 0.8571428571428571,
    "recall": 1.0,
    "f1-score": 0.923076923076923,
    "support": 6,
    "confused_with": {}
  },
  "remote_desktop_connection": {
    "precision": 1.0,
    "recall": 1.0,
    "f1-score": 1.0,
    "support": 7,
    "confused_with": {}
  },
  "two_factor_authentication": {
    "precision": 1.0,
    "recall": 1.0,
    "f1-score": 1.0,
    "support": 8,
    "confused_with": {}
  },
  "mood_unhappy": {
    "precision": 1.0,
    "recall": 1.0,
    "f1-score": 1.0,
    "support": 14,
    "confused_with": {}
  },
  "antivirus_updates_check": {
    "precision": 1.0,
    "recall": 1.0,
    "f1-score": 1.0,
    "support": 7,
    "confused_with": {}
  },
  "query_configure_port_forwarding": {
    "precision": 1.0,
    "recall": 1.0,
    "f1-score": 1.0,
    "support": 3,
    "confused_with": {}
  },
  "greet": {
    "precision": 1.0,
    "recall": 1.0,
    "f1-score": 1.0,
    "support": 13,
    "confused_with": {}
  },
  "new_user_account_request": {
    "precision": 1.0,
    "recall": 1.0,
    "f1-score": 1.0,
    "support": 6,
    "confused_with": {}
  },
  "cat_no": {
    "precision": 1.0,
    "recall": 0.3333333333333333,
    "f1-score": 0.5,
    "support": 3,
    "confused_with": {
      "cat_yes": 2
    }
  },
  "hotfix_vs_service_pack": {
    "precision": 1.0,
    "recall": 1.0,
    "f1-score": 1.0,
    "support": 6,
    "confused_with": {}
  },
  "network_connectivity_troubleshoot": {
    "precision": 1.0,
    "recall": 1.0,
    "f1-score": 1.0,
    "support": 6,
    "confused_with": {}
  },
  "troubleshoot_dns_server": {
    "precision": 1.0,
    "recall": 1.0,
    "f1-score": 1.0,
    "support": 4,
    "confused_with": {}
  },
  "software_updates_installation": {
    "precision": 1.0,
    "recall": 1.0,
    "f1-score": 1.0,
    "support": 6,
    "confused_with": {}
  },
  "troubleshoot_dns_probe": {
    "precision": 1.0,
    "recall": 1.0,
    "f1-score": 1.0,
    "support": 4,
    "confused_with": {}
  },
  "goodbye": {
    "precision": 1.0,
    "recall": 1.0,
    "f1-score": 1.0,
    "support": 10,
    "confused_with": {}
  },
  "query_forgot_wifi_password": {
    "precision": 1.0,
    "recall": 0.6666666666666666,
    "f1-score": 0.8,
    "support": 3,
    "confused_with": {
      "network_password_reset": 1
    }
  },
  "change_flight": {
    "precision": 1.0,
    "recall": 1.0,
    "f1-score": 1.0,
    "support": 3,
    "confused_with": {}
  },
  "backup_restore_process": {
    "precision": 1.0,
    "recall": 1.0,
    "f1-score": 1.0,
    "support": 6,
    "confused_with": {}
  },
  "thank_you": {
    "precision": 1.0,
    "recall": 1.0,
    "f1-score": 1.0,
    "support": 5,
    "confused_with": {}
  },
  "affirm": {
    "precision": 0.8333333333333334,
    "recall": 1.0,
    "f1-score": 0.9090909090909091,
    "support": 5,
    "confused_with": {}
  },
  "browser_cache_and_cookies_clearing": {
    "precision": 1.0,
    "recall": 1.0,
    "f1-score": 1.0,
    "support": 6,
    "confused_with": {}
  },
  "wifi_signal_optimization": {
    "precision": 1.0,
    "recall": 1.0,
    "f1-score": 1.0,
    "support": 7,
    "confused_with": {}
  },
  "apple": {
    "precision": 1.0,
    "recall": 1.0,
    "f1-score": 1.0,
    "support": 5,
    "confused_with": {}
  },
  "explain_error_404": {
    "precision": 1.0,
    "recall": 1.0,
    "f1-score": 1.0,
    "support": 4,
    "confused_with": {}
  },
  "deny": {
    "precision": 1.0,
    "recall": 1.0,
    "f1-score": 1.0,
    "support": 7,
    "confused_with": {}
  },
  "query_network_adapter_drivers": {
    "precision": 1.0,
    "recall": 1.0,
    "f1-score": 1.0,
    "support": 3,
    "confused_with": {}
  },
  "strong_password_creation": {
    "precision": 1.0,
    "recall": 1.0,
    "f1-score": 1.0,
    "support": 6,
    "confused_with": {}
  },
  "cat_yes": {
    "precision": 0.6,
    "recall": 1.0,
    "f1-score": 0.7499999999999999,
    "support": 3,
    "confused_with": {}
  },
  "accuracy": 0.9779411764705882,
  "macro avg": {
    "precision": 0.9795845997973658,
    "recall": 0.9627659574468085,
    "f1-score": 0.9604108657300147,
    "support": 272
  },
  "weighted avg": {
    "precision": 0.9838585434173669,
    "recall": 0.9779411764705882,
    "f1-score": 0.9741793133337251,
    "support": 272
  },
  "micro avg": {
    "precision": 0.9779411764705882,
    "recall": 0.9779411764705882,
    "f1-score": 0.9779411764705882,
    "support": 272
  }
}